findLyrics/__init__.py
findLyrics/findLyrics.py
findLyrics-1.1.0.dist-info/LICENSE
findLyrics-1.1.0.dist-info/METADATA
findLyrics-1.1.0.dist-info/WHEEL
findLyrics-1.1.0.dist-info/top_level.txt
findLyrics-1.1.0.dist-info/RECORD
