Metadata-Version: 2.1
Name: findLyrics
Version: 1.1.0
Summary: Python Lyrics Scrapper
Home-page: https://github.com/sirKiraUzumaki/lyrics_hunter
Author: Ayush Lakra
Author-email: ayushlakra846@gmail.com
License: MIT
Platform: UNKNOWN
Requires-Python: >=3.7
Requires-Dist: beautifulsoup4
Requires-Dist: requests
